cqlmapper/__init__.py
cqlmapper/batch.py
cqlmapper/columns.py
cqlmapper/connection.py
cqlmapper/functions.py
cqlmapper/management.py
cqlmapper/models.py
cqlmapper/operators.py
cqlmapper/query.py
cqlmapper/query_set.py
cqlmapper/statements.py
cqlmapper/usertype.py
tests/__init__.py
tests/integration/__init__.py
tests/integration/base.py
tests/integration/test_batch_query.py
tests/integration/test_consistency.py
tests/integration/test_ifexists.py
tests/integration/test_ifnotexists.py
tests/integration/test_lwt_conditional.py
tests/integration/test_timestamp.py
tests/integration/test_ttl.py
tests/integration/columns/__init__.py
tests/integration/columns/test_container_columns.py
tests/integration/columns/test_counter_column.py
tests/integration/columns/test_static_column.py
tests/integration/columns/test_validation.py
tests/integration/columns/test_value_io.py
tests/integration/management/__init__.py
tests/integration/management/test_compaction_settings.py
tests/integration/management/test_management.py
tests/integration/model/__init__.py
tests/integration/model/test_class_construction.py
tests/integration/model/test_equality_operations.py
tests/integration/model/test_model.py
tests/integration/model/test_model_io.py
tests/integration/model/test_udts.py
tests/integration/model/test_updates.py
tests/integration/model/test_value_lists.py
tests/integration/operators/__init__.py
tests/integration/operators/test_where_operators.py
tests/integration/query/__init__.py
tests/integration/query/test_datetime_queries.py
tests/integration/query/test_queryoperators.py
tests/integration/query/test_queryset.py
tests/integration/query/test_updates.py
tests/integration/statements/__init__.py
tests/integration/statements/test_assignment_clauses.py
tests/integration/statements/test_base_clause.py
tests/integration/statements/test_base_statement.py
tests/integration/statements/test_delete_statement.py
tests/integration/statements/test_insert_statement.py
reddit_cqlmapper-0.3.0.dist-info/LICENSE
reddit_cqlmapper-0.3.0.dist-info/METADATA
reddit_cqlmapper-0.3.0.dist-info/WHEEL
reddit_cqlmapper-0.3.0.dist-info/top_level.txt
reddit_cqlmapper-0.3.0.dist-info/RECORD
