Metadata-Version: 2.1
Name: reddit-cqlmapper
Version: 0.3.0
Summary: a fork of cqlengine modified to work in baseplate.py applications
Home-page: https://github.com/reddit/cqlmapper
Author: reddit
License: UNKNOWN
Platform: UNKNOWN
Classifier: Development Status :: 5 - Production/Stable
Classifier: License :: OSI Approved :: Apache Software License
Classifier: Topic :: Database
Classifier: Topic :: Software Development :: Libraries
Requires-Dist: cassandra-driver
Requires-Dist: six (>=1.6)
